src/GoScrape.py
src/__init__.py
src/main.py
src/pipe/DemoDownloader.py
src/pipe/EventGatherer.py
src/pipe/EventType.py
src/pipe/MatchGatherer.py
src/pipe/__init__.py
goscrape-0.1.3.dist-info/LICENSE
goscrape-0.1.3.dist-info/METADATA
goscrape-0.1.3.dist-info/WHEEL
goscrape-0.1.3.dist-info/entry_points.txt
goscrape-0.1.3.dist-info/top_level.txt
goscrape-0.1.3.dist-info/RECORD
