Metadata-Version: 2.1
Name: goscrape
Version: 0.1.3
Summary: A universal scraping tool to acquire CS:GO demofiles from professional esports events provided by hltv.org
Author: Moritz Steigerwald
Author-email: moritz.steigerwald@studmail.uni-wuerzburg.de
Project-URL: Issues, https://github.com/mo-cmyk/goscrape/issues
Project-URL: GitHub, https://github.com/mo-cmyk/goscrape
Classifier: Programming Language :: Python :: 3
Classifier: License :: OSI Approved :: MIT License
Classifier: Operating System :: OS Independent
License-File: LICENSE
Requires-Dist: beautifulsoup4
Requires-Dist: requests
Requires-Dist: tqdm
